pico_server/__init__.py
pico_server/pico_server.py
pico_server-0.0.1.dist-info/LICENSE
pico_server-0.0.1.dist-info/METADATA
pico_server-0.0.1.dist-info/WHEEL
pico_server-0.0.1.dist-info/top_level.txt
pico_server-0.0.1.dist-info/RECORD
